JPyDB/JPyDBClient.py
JPyDB/JPyDBManager.py
JPyDB/JPyDBServer.py
JPyDB/__init__.py
jpydb-0.0.7.dist-info/METADATA
jpydb-0.0.7.dist-info/WHEEL
jpydb-0.0.7.dist-info/entry_points.txt
jpydb-0.0.7.dist-info/licenses/LICENSE
jpydb-0.0.7.dist-info/RECORD
