Metadata-Version: 2.3
Name: JPyDB
Version: 0.0.7
Summary: Python library to create and manage databases in Json
Project-URL: GitHub, https://github.com/Manu-Sanchez/JPyDB
Project-URL: Linkendin, https://www.linkedin.com/in/manuel-s%C3%A1nchez-mascarell-2a2277195/
Author-email: Manuel Sánchez Mascarell <manusanchezmascarell@gmail.com>
License-File: LICENSE
Classifier: License :: OSI Approved :: MIT License
Classifier: Operating System :: OS Independent
Classifier: Programming Language :: Python :: 3
Requires-Python: >=3.8
